dominoes/__init__.py
dominoes/board.py
dominoes/domino.py
dominoes/exceptions.py
dominoes/game.py
dominoes/hand.py
dominoes/players.py
dominoes/result.py
dominoes/search.py
dominoes/series.py
dominoes/skinny_board.py
dominoes-6.1.0.data/scripts/dominoes
dominoes-6.1.0.dist-info/LICENSE.txt
dominoes-6.1.0.dist-info/METADATA
dominoes-6.1.0.dist-info/WHEEL
dominoes-6.1.0.dist-info/top_level.txt
dominoes-6.1.0.dist-info/RECORD
