Metadata-Version: 2.1
Name: dominoes
Version: 6.1.0
Summary: A Python library for the game of dominoes, with an accompanying CLI and AI players.
Home-page: https://github.com/abw333/dominoes
Author: Alan Wagner
Author-email: alanwagner333@gmail.com
License: MIT
Platform: UNKNOWN
